{
    "Name": "Spynorsk",
    "Fallback": "Norwegian",
    "Translations": {
        "language_spynorsk": "Nynorsk",
        "caption_absorbingproj": "oppsugande skot",
        "caption_agreeing": "enig",
        "caption_alerted": "åtvara",
        "#piece_sapcollector_check": "Sjekk utvinnaren",
        "alternate_key_label": "Alternativ funksjon: +",
        "ammo_arrows": "piler",
        "ammo_bolts": "boltar",
        "ammo_turretbolt": "Svartmetallmissil",
        "ammo_turretboltwood": "Tremissil",
        "ancient_chest": "Eldgamal Likkiste",
        "animal_fish": "Fisk",
        "animal_fish1": "Tryte",
        "animal_fish2": "Gjedde",
        "animal_fish3": "Tunfisk",
        "animal_fish4": "Tetra",
        "animal_fish5": "Trollfisk",
        "animal_fish6": "Kjempesild",
        "animal_fish7": "Åbor",
        "animal_fish8": "Koralltorsk",
        "animal_fish9": "Ljosfisk",
        "animal_fish10": "Nordlaks",
        "animal_fish11": "Magmafisk",
        "animal_fish12": "Kulefisk",
        "base_item_modifier": "Utmatting for gjenstand",
        "biome_ashlands": "Oskeheim",
        "biome_blackforest": "Svartskog",
        "biome_darklands": "Mørkeland",
        "biome_deepnorth": "Det Djupe Nord",
        "biome_edge": "Verdsranden",
        "biome_forest": "Skog",
        "biome_heath": "Hei",
        "biome_meadows": "Eng",
        "biome_mistlands": "Skoddeheim",
        "biome_mountain": "Fjell",
        "biome_ocean": "Hav",
        "biome_plains": "Stepper",
        "biome_swamp": "Myr",
        "boss_hive_end": "Me er spreidde.",
        "boss_hive_start": "Me er samla.",
        "button_a": "A",
        "button_b": "B",
        "button_back": "Attende",
        "button_lalt": "L-Alt",
        "button_lb": "LB",
        "button_lcommand": "L-Command",
        "button_lctrl": "L-Ctrl",
        "button_ls": "LS",
        "button_lshift": "L-Shift",
        "button_mouse0": "Mouse-1",
        "button_mouse1": "Mouse-2",
        "button_mouse2": "Mouse-3",
        "button_ps_a": "✕",
        "button_ps_b": "○",
        "button_ps_back": "Share",
        "button_ps_lb": "L1",
        "button_ps_ls": "L3",
        "button_ps_rb": "R1",
        "button_ps_rs": "R3",
        "button_ps_start": "Options",
        "button_ps_x": "▫",
        "button_ps_y": "△",
        "button_ralt": "R-Alt",
        "button_rb": "RB",
        "button_rcommand": "R-Command",
        "button_rctrl": "R-Ctrl",
        "button_return": "Return",
        "button_rs": "RS",
        "button_rshift": "R-Shift",
        "button_space": "Mellomrom",
        "button_start": "Start",
        "button_x": "X",
        "button_y": "Y",
        "caption_altar_empowered": "Altar styrkja",
        "caption_arriving": "kjem",
        "caption_atgeir": "Atgeir",
        "caption_attacking": "gjer åtak",
        "caption_awakening": "vaknar",
        "caption_axe": "Øks",
        "caption_barking": "bjeffar",
        "caption_biting": "bit",
        "caption_blockedattack": "Åtak avverja",
        "caption_blocking": "verjar",
        "caption_born": "vert fødd",
        "caption_bow": "Boge",
        "caption_breakingapart": "riv sund",
        "caption_breathingfire": "pustar eld",
        "caption_bubbling": "koker",
        "caption_building": "byggjer",
        "caption_burningfood": "mat vert svidd",
        "caption_burp": "rapar",
        "caption_burrowing": "grev",
        "caption_bye": "seier ha det",
        "caption_calling": "kallar",
        "caption_callingforaid": "kallar på hjelp",
        "caption_casting": "kastar",
        "caption_castingmagic": "kallar fram magi",
        "caption_castingspell": "kallar fram seiding",
        "caption_catchfire": "tek fyr",
        "caption_cawing": "seier kra",
        "caption_charging": "stormar",
        "caption_chittering": "kvitter",
        "caption_closing": "lukkar",
        "caption_creaking": "knirkar",
        "caption_destroyed": "øydelagd",
        "caption_dispersing": "spreier",
        "caption_dodging": "vik unna",
        "caption_donecooking": "mat ferdigsteikt",
        "caption_doorclose": "Dør vert lukka",
        "caption_dooropen": "Dør vert opna",
        "caption_drawn": "vert dregen",
        "caption_droppingitem": "slepper gjenstand",
        "caption_dying": "døyr",
        "caption_eating": "et",
        "caption_exploding": "sprengjer",
        "caption_explosion": "Sprenging",
        "caption_firework_explode": "Fyrverk sprengjer",
        "caption_firing": "skyt",
        "caption_fizzling": "freser",
        "caption_food_burnt": "Mat brunnen",
        "caption_food_done": "Mat ferdig",
        "caption_fueladded": "Brensle lagt til",
        "caption_gateclose": "Grind vert lukka",
        "caption_gateopen": "Grind vert opna",
        "caption_gettinghit": "vert slegen",
        "caption_ghostnoises": "sus",
        "caption_groaning": "styn",
        "caption_growing": "veks",
        "caption_growling": "rumlar",
        "caption_grumbling": "rumling",
        "caption_grunting": "gryntar",
        "caption_healing": "lækjer",
        "caption_hello": "helsar",
        "caption_hit": "slag",
        "caption_hitting": "slår",
        "caption_howling": "ular",
        "caption_hurt": "såra",
        "caption_iceshatter": "Is som brest",
        "caption_inhaling": "andar inn",
        "caption_itemcrafted": "Gjenstand laga",
        "caption_jumping": "hoppar",
        "caption_knife": "Kniv",
        "caption_laughing": "ler",
        "caption_levelup": "Evne betra!",
        "caption_lightingfire": "gjer opp eld",
        "caption_linebreak": "snøre brest",
        "caption_loaded": "ladd",
        "caption_meteor_exploding": "Meteor sprengjer",
        "caption_moving": "rører seg",
        "caption_opening": "opnar",
        "caption_parried": "Åtak stagga",
        "caption_platform_crumbling": "Lavahelle smuldrar opp",
        "caption_platform_rising": "Helle stig",
        "caption_player": "Spelar",
        "caption_portalopen": "Portal vert opna",
        "caption_potion": "Trolldrykk drukken",
        "caption_projexploding": "skot sprengjer",
        "caption_puking": "Spying",
        "caption_punching": "Slag",
        "caption_rattling": "skramlar",
        "caption_ravencaw": "Ramn skrik",
        "caption_ravenflap": "Ramn flaksar",
        "caption_recharging": "lar",
        "caption_refilled": "fylt på nytt",
        "caption_refueled": "brensle fylt på",
        "caption_reloading": "lar",
        "caption_repaired": "gjenstand vølt",
        "caption_rising": "stig",
        "caption_rockdestroyed": "Stein knusar",
        "caption_ruminating": "tygg drøv",
        "caption_screeching": "skrik",
        "caption_seagull": "Måse",
        "caption_shaking": "skjelv",
        "caption_shattering": "vert knust",
        "caption_shedding": "skalar av???",
        "caption_shivering": "skjelv",
        "caption_shouting": "roper",
        "caption_shuttingdown": "stengjer ned",
        "caption_sighing": "sukkar",
        "caption_snarling": "snerrar",
        "caption_spear": "Spjut",
        "caption_spinning": "spinn",
        "caption_spitexploding": "spytt sprengjer",
        "caption_spitting": "spyttar",
        "caption_splashing": "skvett",
        "caption_sputtering": "sprutar",
        "caption_squawking": "skravlande fugl",
        "caption_startup": "tek til å virke",
        "caption_stomping": "trampar",
        "caption_summoning": "kallar fram",
        "caption_sweeping": "sopar",
        "caption_swiping": "sveiper",
        "caption_swung": "vert svinga",
        "caption_takingdamage": "tek skade",
        "caption_takingoff": "lyfter frå bakken",
        "caption_talking": "skravlar",
        "caption_throwing": "kastar",
        "caption_thunder": "Fjern tore",
        "caption_tilling": "pløyer",
        "caption_trading": "er nøgd med byte",
        "caption_treefall": "Tre fell",
        "caption_used": "nytta",
        "charredfortress": "Svidd festning",
        "chat_entermessage": "Skriv melding",
        "chat_entertext": "Skriv tekst...",
        "chat_kill": "Tak livet av deg sjølv",
        "chat_resetspawn": "Attendeset byrjestad",
        "chat_shout": "Rop",
        "chat_whisper": "Kviskre",
        "customization_beard01": "Majestetisk",
        "customization_beard02": "Tvillingfletter",
        "customization_beard03": "Stutt",
        "customization_beard04": "Slett",
        "customization_beard05": "Flette",
        "customization_beard06": "Laus Flette",
        "customization_beard07": "Kløyvd Barbering",
        "customization_beard08": "Tjukt",
        "customization_beard09": "Trubadur",
        "customization_beard10": "Toppflette",
        "customization_beard11": "Andletvarmar",
        "customization_beard12": "Kongeleg",
        "customization_beard13": "Trillingar",
        "customization_beard14": "Kløyvd Flette",
        "customization_beard15": "Lita Flette",
        "customization_beard16": "Hòlebuar",
        "customization_beard17": "Skikkeleg",
        "customization_beard18": "Jarlfletter",
        "customization_beard19": "Buskete",
        "customization_beard20": "Taggete",
        "customization_beard21": "Ryddig",
        "customization_beard22": "Bart",
        "customization_beard23": "Smulefangar",
        "customization_beard24": "Voksa",
        "customization_beard25": "Stussa",
        "customization_beard26": "Snurrebart",
        "customization_hair01": "Forblåse",
        "customization_hair02": "Høg hestehale",
        "customization_hair03": "Musefletter",
        "customization_hair04": "Låg hestehale",
        "customization_hair05": "Stutt",
        "customization_hair06": "Langt og Laust",
        "customization_hair07": "Drakedrepar",
        "customization_hair08": "Skilt",
        "customization_hair09": "Gamle Einauge",
        "customization_hair10": "Sveipt Til Sides",
        "customization_hair11": "Lang Flette",
        "customization_hair12": "Matroneaktig",
        "customization_hair13": "Tvillingfletter",
        "customization_hair14": "Fartsdemon",
        "customization_hair15": "Samla Krøller",
        "customization_hair16": "Samla Fletter",
        "customization_hair17": "Skikkelege Fletter",
        "customization_hair18": "Kongelege Fletter",
        "customization_hair19": "Målarfletter",
        "customization_hair20": "Ryddige Krøller",
        "customization_hair21": "Tvillingknutar",
        "customization_hair22": "Enkel Knut",
        "customization_hair23": "Stutte Krøller",
        "customization_hair24": "Fletta og Barbert",
        "customization_hair25": "Knut",
        "customization_hair26": "Korte Dreads",
        "customization_hair27": "Styrkefletter",
        "customization_hair28": "Kjøpmannsfletter",
        "customization_hair29": "Sleik",
        "customization_hair30": "Lause Bølgjer",
        "customization_hair31": "Samla Dreads",
        "customization_hair32": "Hockey",
        "customization_hair33": "Vinlandsbarbert",
        "customization_hair34": "Herskar",
        "customization_nobeard": "Ikkje Skjegg",
        "customization_nohair": "Skalla",
        "deadspeak_bonemass": "Takk, krigar. Me som levde vidare i denne forma vart lenge nekta freden av å døy. No går me...",
        "deadspeak_eikthyr": "Så du vart dauden min? Du ser så liten og veik ut… Odin kan ha knust denne forma, men fortel han at villmarka aldri vil knele...",
        "deadspeak_elder": "Lille sak av blod og bein, eg skulle ha brekt deg som ein kvist! No som eg visnar og døyr, la det store treet ta meg...",
        "deadspeak_fader": "Eg fylgde ein falsk skjebne, og han gav meg ikkje anna enn øydelegging. Tilgje meg, min kjære...",
        "deadspeak_fish_shared1": "Don't worry. Be happy.",
        "deadspeak_fish_shared2": "Ta meg med til elva... Kast meg i vatnet...",
        "deadspeak_fish1": "USIKKERT I'm a perch, not a bass!",
        "deadspeak_fish10": "Til laks åt alle kan ingen gjera.",
        "deadspeak_fish11": "La meg kvile ved elden...",
        "deadspeak_fish12": "USIKKERT Have you seen my friend around? Her name is Anika.",
        "deadspeak_fish2": "USIKKERT You're supposed to put heads on a pike, not put a pike on a wall...",
        "deadspeak_fish3": "USIKKERT I've got this tune stuck in my head...",
        "deadspeak_fish4": "Det er så kaldt... Og mørkt... Men eg likar det slik.",
        "deadspeak_fish5": "Hold opp med den lokkinga!",
        "deadspeak_fish6": "Kva for ei ekkel lukt? Det er da vel ikkje meg!",
        "deadspeak_fish7": "Eg er daud, men ikkje vekke. Kan du ikkje setje meg fri frå denne skjærselden?",
        "deadspeak_fish8": "Har du nokon gong lurt på kva ein finn på botnen av havet? Gjer ikkje det. Slikt er det bettre å ikkje vete.",
        "deadspeak_fish9": "Kan du sjå lyset? Det kallar på deg...",
        "deadspeak_hive": "Du trur at du slo oss? Da tek du feil... Me er framleis, og vil for alltid vere bolet - og bolet er uslåeleg.",
        "deadspeak_moder": "Stikk byrgskapen i slira, Odinsbarn! Mitt lange velde er over, men dei som kjem etter meg er enda større...",
        "deadspeak_queen": "Sei til Odin at min ætt skal bere fram enda ein... Ei dronning døyr aldri.",
        "deadspeak_yagluth": "Kjem du for å braute, lille sak? Veit du kor mange gonger eg har vore drepen, knust, bannlyst, brent og gravlagt? Du er ikkje den fyrste og du vert ikkje den siste.",
        "dream_ashlands01": "Du vakner i ein draum om mørke himlar og rullande skyer. Natt på fjelltoppen, med ei enkel kappe pakka tett kring deg. Himmelen brest av tore. Varme glør regner ut av rifta og øydelegger deg i draumen på ein augneblink…",
        "dream_ashlands02": "I draumen sit du krøkt i midten av ei vid og mørk hòle, medan eit veldig beist krinsar om deg med mørkret på slep. Logar av smaragdeld flicker at its edges and the growl of its throat lingers long into the waking day…",
        "dream_ashlands03": "Du drøymer at du et villsvin i eit gilde. Det er enkel, men framifrå mat. Om berre alle draumar hadde vore slik.",
        "dream_ashlands04": "Nine maidens in robes of white dance barefoot at midnight. Nine wolves hunt a white hart in the greenwood. Nine bells ring out on the mountainside and you awake.",
        "dream_bonemass01": "You dream of a hundred ghosts crowding thickly around your bedside, seeking warmth and life until something thumps deep below the ground and they jump like crumbs on a drumskin and are gone.",
        "dream_eikthyr01": "You dream of running through a meadow, the sky alight with pale fire. There is a thunder of hoofbeats behind you but when you turn, nothing is there. You awaken with your heart pounding in your chest.",
        "dream_elder01": "In your dream, the forest rises before you, dragging the trees upward like a cloak, its dark mass hiding the stars. At the mountain's peak, vast antlers frame the moon...",
        "dream_mistlands01": "In your dream, you walk through a hall of smiling warriors and gracious maidens. You join with their mirth until you realise that you are naked and the small bronze shield you are carrying is not enough to cover your shame. You greet the morning with gratitude.",
        "dream_mistlands02": "Dark-eyed Loki approaches you in your dream and gifts you a ring for each hand. He tells you that as long as they stay on your fingers, you will never hear an insulting word again. You wake with your fingers in your ears.",
        "dream_mistlands03": "You climb a winding staircase, curled tightly within a tall tower, until you arrive at the top and look out over an endless forest. The wind blows green waves across the tree-tops and beneath the surface, dark shapes tir...",
        "dream_moder01": "You dream that you are flying over mountaintops, all of Valheim spread out below you. As you wheel and dive in the cold air, a great shape soars up past you to block the sun. In the darkness, it speaks. Seek me.",
        "dream_random01": "You dream of a river running uphill, of green shoots turning downward into the earth…",
        "dream_random02": "Once again, you run at the head of your warriors, the weight of your father's axe in your hand. You wake with the war-cry on your lips…",
        "dream_random03": "In your dream, you sit beside a fire in a great hall, surrounded by the chatter of familiar voices. Their faces blur like smoke and their names slip your mind, but the warmth of their memory lingers…",
        "dream_random04": "You stand at the prow of a leaping ship, the salt spray before you and the joyful shriek of gulls above. Folded within a dream, you remember what it was like to be alive in the land of your birth.",
        "dream_random05": "You dream of a great tree reaching out through the night. One half of its branches crackle with flames, the others are green with leaves.",
        "dream_random06": "Amidst the crash of arms, on the dark and glimmering plain of sleep, a face swells snarling before you. Your shield arm hangs limp, your spear is broken. You welcome the cold blade when it comes. From a dream of death, you awaken to death itself.",
        "dream_random07": "You dream you are lying on your back in a meadow, gazing upward at the clouds. Your name is nothing, your mind is free of thought. But there is a warm hand in yours. In the dream, you are laughing. But when you awaken, you find your face damp with tears.",
        "dream_random08": "On a boat carved from dark wood, beneath ragged sails, you lie with your arms folded across your chest. Blurred faces, like thumbprints on the darkness, croon familiar songs as they push you out to float on a sea as black and flat as glass.",
        "dream_random09": "You lie on the battlefield, dreaming eyes turned upward to a sky veiled by smoke. The calls of your warriors grow fainter and your eyes close for a second time. Great talons slide beneath you and you feel yourself rising, lifted from your body like a babe from its crib…",
        "dream_random10": "You fall into the deep well of sleep and dream only of darkness.",
        "dream_random11": "You dream of a bright hall filled with gracious warriors and fair maidens. The air hums with song, the boards groan under the weight of steaming dishes, the mead flows like water. You awake slowly with the laughter still ringing in your ears…",
        "dream_random12": "You sleep in fits and fretful dreams, the weight of the nightmare heavy on your chest. When morning comes, you greet it with relief.",
        "dream_random13": "Sleep is a river and dreams are live fish. You wake in the morning with your net empty.",
        "dream_random14": "You dream you are hunting with your companions, running high over green hills and down through mist-haunted valleys. Ahead of you, your prey stumbles and you leap forward, sinking your teeth into warm flesh. When you wake, the taste of metal lingers in your mouth.",
        "dream_random15": "Du drøymer at du går gjennom ein snødekt skog, og støyter på eit nakent barn som sit og stør seg mot eit tre. Auga hans er lukka, men brystet rører seg med andedrag. Du bøyer deg ned jamsides han, og skjøner at han har sove der, biande, i fleire hundre år. Når du tek han på aksla, vaknar de båe. Jævla pedo.",
        "dream_random16": "You dream of a mighty bear, sleeping deep below the earth in the winter of the world. It turns in its sleep, folds upon folds of flesh and fur. It has no head, no limbs. A vast mass of bear flesh, mercifully quiet.",
        "dream_random17": "You fall asleep planning your next day's labor and in your dreams you complete it, hewing wood, foraging for food and hunting after swift deer. You return home exhausted but happy, only to awaken and find the day is still ahead of you...",
        "dream_yagluth01": "In a chamber hung with golden drapes, you kneel before the throne of a veiled king. Sleep is but a mask, he tells you, lifting the veil slowly. You wake screaming.",
        "dvergr_buff": "Dvergkraft",
        "dvergr_buff_description": "Du er påverka av ei framand dvergkraft som gjer deg sterkare.",
        "enemy_abomination": "Uhyre",
        "enemy_asksvin": "Osksvin",
        "enemy_asksvin_hatchling": "Nyklekt Osksvin",
        "enemy_babyseeker": "Droneyngel",
        "enemy_bat": "Skinnvengje",
        "enemy_bjorn": "Bjørn",
        "enemy_blob": "Klatt",
        "enemy_blobelite": "Tytar",
        "enemy_blobfrost": "Frosen Klatt",
        "enemy_bloblava": "Lavaklatt",
        "enemy_blobtar": "Tjøreklatt",
        "enemy_boar": "Villsvin",
        "enemy_boarpiggy": "Villsvinunge",
        "enemy_bonemass": "Beinmassen",
        "enemy_bonemawserpent": "Beingap",
        "enemy_boss_bonemass_deathmessage": "Massen slutar å vri seg",
        "enemy_boss_bonemass_spawnmessage": "Massen rører seg",
        "enemy_boss_dragon_deathmessage": "Moder græt",
        "enemy_boss_dragon_spawnmessage": "Moder er forbanna",
        "enemy_boss_fader_alertmessage": "Smaragdelden blussar opp",
        "enemy_boss_fader_deathmessage": "Smaragdelden sloknar",
        "enemy_boss_goblinking_deathmessage": "Sjela til Yagluth er slegen",
        "enemy_boss_goblinking_spawnmessage": "Den vridde sjela til Yagluth er påkalla",
        "enemy_boss_queen_alertmessage": "Dronninga vil ha alt saman",
        "enemy_boss_queen_deathmessage": "Lenge leve Dronninga",
        "enemy_charred": "Svidd",
        "enemy_charred_archer": "Svidd Skarpskyttar",
        "enemy_charred_grunt": "Svidd Kjeltring",
        "enemy_charred_mage": "Svidd Trollmann",
        "enemy_charred_melee": "Svidd Krigar",
        "enemy_charred_melee_Dyrnwyn": "&lt;color=orange&gt;Fyrst Reto",
        "enemy_charred_melee_Fader": "Framkalla Svidd Krigar",
        "enemy_charred_twitcher": "Svidd Rykkjar",
        "enemy_charred_twitcher_summoned": "Framkalla Rykkjar",
        "enemy_charredspawnercross": "Nidfigur",
        "enemy_charredtwitcherspawner": "Plagemerke",
        "enemy_chicken": "Kjukling",
        "enemy_deathsquito": "Daudemygg",
        "enemy_deer": "Rådyr",
        "enemy_dragon": "Moder",
        "enemy_drake": "Drake",
        "enemy_draugr": "Draug",
        "enemy_draugrelite": "Elitedraug",
        "enemy_draugrspawner": "Likhaug",
        "enemy_dvergr": "Dvergrømling",
        "enemy_dvergr_mage": "Dvergtrollmann",
        "enemy_dvergrs": "Dverg",
        "enemy_eikthyr": "Eikthyr",
        "enemy_fader": "Fader",
        "enemy_fader_codename": "Smaragdelden",
        "enemy_fallenvalkyrie": "Fallen Valkyrie",
        "enemy_fenring": "Fenring",
        "enemy_fenringcultist": "Sekterist",
        "enemy_fenringcultist_hildir": "&lt;color=orange&gt;Geirrhafa",
        "enemy_gdking": "Den Eldste",
        "enemy_gemgoblin": "Riktig Fuling",
        "enemy_ghost": "Skrømt",
        "enemy_gjall": "Gjall",
        "enemy_goblin": "Fuling",
        "enemy_goblin_hildir": "&lt;color=orange&gt;Zil",
        "enemy_goblinbrute": "Fulingberserk",
        "enemy_goblinbrute_hildir": "&lt;color=orange&gt;Thungr",
        "enemy_goblinbrute_hildircombined": "&lt;color=orange&gt;Zil &amp; Thungr",
        "enemy_goblinking": "Yagluth",
        "enemy_goblinshaman": "Fulingsjaman",
        "enemy_greydwarf": "Grådverg",
        "enemy_greydwarfbrute": "Grådvergbølle",
        "enemy_greydwarfshaman": "Grådvergsjaman",
        "enemy_greydwarfspawner": "Grådvergbol",
        "enemy_greyling": "Gråling",
        "enemy_hare": "Hare",
        "enemy_hen": "Høne",
        "enemy_kvastur": "Kvastur",
        "enemy_kvastur_lore": "Fylgjesveinen til ei volve må vere laga av eit kraftig emne.",
        "enemy_leech": "Igle",
        "enemy_lox": "Stutfisle",
        "enemy_loxcalf": "Stutfislekalv",
        "enemy_mistile": "Skoddeskot",
        "enemy_morgen": "Morgon",
        "enemy_neck": "Vassvette",
        "enemy_seeker": "Drone",
        "enemy_seekerbrute": "Dronesoldat",
        "enemy_seekerqueen": "Dronninga",
        "enemy_serpent": "Orm",
        "enemy_skeleton": "Beinrangel",
        "enemy_skeleton_summoned": "Beinrangel???",
        "enemy_skeletonfire": "&lt;color=orange&gt;Brenna",
        "enemy_skeletonpoison": "Ròtne Leivder",
        "enemy_skeletonspawner": "Ond Beinhaug",
        "enemy_stonegolem": "Steingolem",
        "enemy_summonedroot": "Framkalla Rot",
        "enemy_summonedtroll": "Framkalla Troll",
        "enemy_surtling": "Surtling",
        "enemy_tick": "Flått",
        "enemy_troll": "Troll",
        "enemy_ulv": "Varulv",
        "enemy_unbjorn": "Brakar",
        "enemy_volture": "Gribb?",
        "enemy_wolf": "Varg",
        "enemy_wolfcub": "Vargekvelp",
        "enemy_wraith": "Attergangar",
        "error_alreadyconnected": "Allereie kopla til",
        "error_banned": "Bannlyst",
        "error_cantrestorebackup": "Greier ikkje gjenopprette sikringskopi!",
        "error_cantrestoremeta": "Greier ikkje gjenopprette metafil!",
        "error_disconnected": "Fråkopla",
        "error_failedconnect": "Greide ikkje å kople til",
        "error_incompatibleversion": "Ukompatibel utgåve",
        "error_kicked": "Du vart sparka frå tenaren.",
        "error_needslocalupdatetojoin": "Du køyrer ei eldre utgåve av Valheim som ikkje er kompatibel med denne tenaren. Oppdater spelet for å kople til denne tenaren.",
        "error_needsserverupdatetojoin": "Denne tenaren køyrer ei eldre utgåve av Valheim som ikkje er kompatibel med utgåva di.",
        "error_nosuitablebackupfound": "Fann ingen eigna sikringskopi!",
        "error_password": "Feil passord",
        "error_platformexcluded": "Tenareigaren lèt ikkje brukarar frå andre plattformar enn den han sjølv nyttar spele på tenaren.",
        "error_serverfull": "Tenaren er full",
        "error_worldfileload": "Feil ved innlasting av verdsfil. Sjekk sikringskopiar!",
        "event_bats_end": "Kjelen roar seg",
        "event_bats_start": "Du rørte i kjelen",
        "event_bonemassarmy_end": "Eima forsvinn",
        "event_bonemassarmy_start": "Ei fælsleg eim kjem frå myra...",
        "event_boss01_end": "Eikthyr er slegen.",
        "event_boss01_start": "Eikthyr har vakna!",
        "event_boss02_end": "Den Eldste er slegen.",
        "event_boss02_start": "Den Eldste har vakna!",
        "event_boss03_end": "Beinmassen er slegen.",
        "event_boss03_start": "Beinmassen har vakna!",
        "event_boss04_end": "Moder er slegen.",
        "event_boss04_start": "Moder har vakna!",
        "event_boss05_end": "Kong Yagluth er slegen.",
        "event_boss05_start": "Kong Yagluth har vakna!",
        "event_caves_end": "Dei ular ikkje meir",
        "event_caves_start": "Du høyrer uling frå djupet...",
        "event_charredarmy_end": "Hæren gjer retrett",
        "event_charredarmy_start": "Den vandaude hæren marsjerer",
        "event_charredspawnerarmy_start": "Dei daude er tilkalla",
        "event_charrespawnerarmy_end": "Dei daude kviler igjen",
        "event_eikthyrarmy_end": "Skapningane roar seg",
        "event_eikthyrarmy_start": "Eikthyr samlar skapningane i skogen",
        "event_foresttrolls_end": "Skjelvinga byrjar å avta",
        "event_foresttrolls_start": "Marka skjelv",
        "event_gdkingarmy_end": "Skogen kviler igjen",
        "event_gdkingarmy_start": "Skogen rører seg...",
        "event_gemgoblin_end": "Du tok dei",
        "event_gemgoblin_start": "Ta dei!",
        "event_ghosts_end": "Du har lyst dei i bann, enn så lenge...",
        "event_ghosts_start": "Du får frysinger nedover ryggen...",
        "event_gjallarmy_end": "Snakkast, Gjall",
        "event_gjallarmy_start": "Kva skjer, Gjall?!",
        "event_goblinarmy_end": "Horden gjer retrett",
        "event_goblinarmy_start": "Horden gjer åtak!",
        "event_hildirboss1_end": "Ho brann seg",
        "event_hildirboss1_start": "Ho nærmar seg!",
        "event_hildirboss2_end": "Du kan slappe av",
        "event_hildirboss2_start": "Du får frysinger...",
        "event_hildirboss3_end": "Du braut reglane... igjen",
        "event_hildirboss3_start": "Dei var brør, mann",
        "event_moderarmy_end": "Den kalde vinden er vekke",
        "event_moderarmy_start": "Ein kald vind blæs frå fjella",
        "event_seekerarmy_end": "Leitinga er over",
        "event_seekerarmy_start": "Dei leitte etter deg",
        "event_skeletons_end": "Beinrangla er lei av å sloss",
        "event_skeletons_start": "Ei beinrangeloverrasking!",
        "event_surtlings_end": "Lukta forsvinn",
        "event_surtlings_start": "Det luktar svovel...",
        "event_wolves_end": "Jakta er omme",
        "event_wolves_start": "Dei jaktar på deg...",
        "faderlocation_bellholder": "Bjøllehaldar",
        "feedback_bug": "Bug",
        "feedback_feedback": "Tilbakemelding",
        "feedback_idea": "Idé",
        "feedback_send": "Send",
        "feedback_subject": "Emne",
        "feedback_text": "Skriv noko",
        "feedback_topic": "Tilbakemelding",
        "fish1_description": "God kvit fisk.",
        "fish10_description": "Denne fisken likar vatnet nesten frose.",
        "fish11_description": "Det vert sagt at denne fisken gyter i flytande magma!",
        "fish12_description": "Veldig god om han er laga til rett, men smaken kan vere litt kvass.",
        "fish2_description": "Ein ferskvassfisk som treng mykje krydder.",
        "fish3_description": "Havets kjukling...",
        "fish4_description": "Han lever heile livet i mørker, så han treng ikkje auge.",
        "fish5_description": "Denne fisken er ein bråkmakar i lokale straumar.",
        "fish6_description": "Om han er sylta, luktar denne fisken verre enn myra han kjem frå.",
        "fish7_description": "Best med mykje kolhydrat!",
        "fish8_description": "Han har sett nokre ting... Nokre veldig fæle ting...",
        "fish9_description": "Ljoset gjer det lettare å sjå det pene lille andletet!",
        "guardianstone_bonemass_desc": "Vandrar, sjå på føtene dine\nSom trår på grava vår\nTusen bein utan kjøt\nVil dra deg under",
        "guardianstone_eikthyr_desc": "Geviret hans er jarngreiner\nDei knuser stein og jamnar fjell med jorda\nHóvane hans er ljoden av tore\nStemmen ein ulande storm",
        "guardianstone_fader_desc": "Ein far, edel og byrg\nHan svevde gjennom himmeleld\nSå senka vanvitet sløret sitt\nOg vreid om hjartevilja hans",
        "guardianstone_hook_activate": "Aktivér kraft",
        "guardianstone_hook_alreadyactive": "Noverande kraft",
        "guardianstone_hook_deactivate": "Slepp laus kraft",
        "guardianstone_hook_name": "Trofékrok",
        "guardianstone_hook_power_activate": "Aktivert",
        "guardianstone_hook_power_deactivate": "Sloppe laus",
        "guardianstone_moder_desc": "Svarte vengjer over måne og sol\nNed frå fjellet kjem vår mor\nTårane hennar vil falle som regn\nRøysta hennar vil kalle oss heim",
        "guardianstone_name": "Offerstein",
        "guardianstone_theelder_desc": "Fyrst av Skogen, Konge av røter\nDrott over dei som bur ved hans føter\nHan spreier sine røter der byar stod\nEt deira kjøt og drikk deira blod",
        "guardianstone_thequeen_desc": "Fødd i rustning\nMor til mange\nDronning utan krone\nHerskar under",
        "guardianstone_trophyplaced": "Forvist ofra",
        "guardianstone_yagluth_desc": "For lenge sidan, ei krone han bar\nUnder kvelvingen, raud som blod\nDet er ikkje meir av alt som han var\nMen sjela hans lever enno",
        "heightmap_issue_message": "USIKKERT To fix a critical issue with the world map not being in sync, small parts of worlds for some players will be changed. Any structures built close to those areas may potentially break. We try our best to ensure that these issues do not happen, but sometimes it’s unavoidable and we are truly sorry for any inconvenience.",
        "hud_addpin": "Legg til merke",
        "hud_altplace": "Veksle plasseringspunkt / innstillinger",
        "hud_altplacement": "Alternativ plasseringsmodus:",
        "hud_autopickup": "Automatisk oppsamling",
        "hud_build": "Bygg",
        "hud_building": "Byggverk",
        "hud_building2": "Tungt Byggverk",
        "hud_buildmenu": "Byggemeny",
        "hud_changeorientation": "Endre lei",
        "hud_copypiece": "Kopiér",
        "hud_crafting": "Utforming",
        "hud_crossoffpin": "Kryss av merke",
        "hud_cyclesnap": "Veksle festepunkt",
        "hud_eitrrequired": "Treng eitr",
        "hud_emotes_blowkiss": "Slengkyss",
        "hud_emotes_bow": "Bukke",
        "hud_emotes_challenge": "Utfordre",
        "hud_emotes_cheer": "Heia",
        "hud_emotes_comehere": "Kjem hit",
        "hud_emotes_cower": "Gøyme seg",
        "hud_emotes_cry": "Gråte",
        "hud_emotes_dance": "Dans",
        "hud_emotes_despair": "Fortviling",
        "hud_emotes_flex": "Vise musklar",
        "hud_emotes_headbang": "Headbang",
        "hud_emotes_kneel": "Knele",
        "hud_emotes_laugh": "Le",
        "hud_emotes_nonono": "Nei nei nei",
        "hud_emotes_point": "Peke",
        "hud_emotes_roar": "Brøl",
        "hud_emotes_shrug": "Trekkje på skuldrene",
        "hud_emotes_sit": "Sitte",
        "hud_emotes_thumbsup": "Tommel opp",
        "hud_emotes_wave": "Vink",
        "hud_equipping": "Nyttar",
        "hud_feasts": "Festmåltid",
        "hud_food": "Mat",
        "hud_furniture": "Innbu",
        "hud_hidden_messagehud_notification": "Skrudde av HUD. Trykk Ctrl + F3 for å skru på",
        "hud_hidden_messagehud_notification_gamepad": "Skrudde av HUD. For å skru på, trykk",
        "hud_hidemap": "Skjul kart",
        "hud_hidepin": "Veksle merke",
        "hud_itemstucktar": "Sit fast i tjøra",
        "hud_loadingrequired": "Våpenet er ikkje ladd",
        "hud_mapday": "Dag",
        "hud_maxsummonsreached": "Daudevekkjaren din er ikkje sterk nok til å kalle på fleire.",
        "hud_maxsummonsreached_greenroots": "Villmarksstaven din er ikkje sterk not til å kalle på fleire.",
        "hud_maxsummonsreached_trollstav": "Trollstaven din er ikkje sterk not til å kalle på fleire.",
        "hud_meads": "Mjød",
        "hud_misc": "Div.",
        "hud_namepin": "Set namn på merket ditt",
        "hud_nothingtobuild": "Ikkje noko å byggje",
        "hud_off": "Av",
        "hud_on": "På",
        "hud_pet": "Klapp",
        "hud_pin_hildir1": "Ulmande Gravkammer",
        "hud_pin_hildir2": "Ulande Hòle",
        "hud_pin_hildir3": "Forsegla Tårn",
        "hud_ping": "Ping",
        "hud_place": "Plassér",
        "hud_powernotready": "Krafta er ikkje klar",
        "hud_publicpos": "Synleg for andre spelarar",
        "hud_ready": "Klar",
        "hud_reloading": "Lastar",
        "hud_remove": "Fjern",
        "hud_removepin": "Fjern merke",
        "hud_rename": "Gje nytt namn",
        "hud_repair": "Vøl",
        "hud_require": "Krev",
        "hud_rotate": "Snu",
        "hud_saddle_already": "har allereie ein sal",
        "hud_saddle_ready": "er klar for å ri",
        "hud_saddle_remove": "Fjern sal",
        "hud_sharedmap": "Kartografibenk",
        "hud_showmap": "Vis kart",
        "hud_snappoint_attach": "Fest",
        "hud_snappoint_bottom": "Bunn",
        "hud_snappoint_center": "Midt",
        "hud_snappoint_corner": "Hyrne",
        "hud_snappoint_edge": "Kant",
        "hud_snappoint_end": "Ende",
        "hud_snappoint_inner": "Indre",
        "hud_snappoint_mid": "Midt",
        "hud_snappoint_top": "Topp",
        "hud_switchcategory": "Byt kategori",
        "hud_switchitem": "Byt gjenstand",
        "hud_tame": "Tam",
        "hud_tamecheck": "Sjekk",
        "hud_tamedone": "er temt",
        "hud_tamefollow": "fylgjer deg",
        "hud_tamefrightened": "Redd",
        "hud_tamehappy": "Glad",
        "hud_tamehungry": "Svolten",
        "hud_tameinprogress": "Ven seg",
        "hud_tamelove": "elskar deg",
        "hud_tamelove2": "elskar deg høgt",
        "hud_tamelove3": "kosar med deg",
        "hud_tameness": "Temming",
        "hud_tamestay": "vert verande",
        "hud_unequipping": "Tek av",
        "hud_wild": "Vill",
        "hud_zoom": "Zoom",
        "hud_zoom_in_out": "Zoom ut/inn",
        "info_label": "Info",
        "interface_leftarrow": "&lt;",
        "interface_rightarrow": "&gt;",
        "invalid_keybind_header": "Ugyldig Tast",
        "invalid_keybind_text": "Du kan ikkje binde denne handlinga til tasten du har valt",
        "inventory_activeeffects": "Aktive verknadar",
        "inventory_blunt": "Slag",
        "inventory_chop": "Hogg",
        "inventory_craftbutton": "Lag",
        "inventory_crafting": "Utforming",
        "inventory_craftingprog": "Lagar",
        "inventory_damage": "Skade",
        "inventory_dmgmod": "Skademodifisering",
        "inventory_drop": "Slepp",
        "inventory_fire": "Eld",
        "inventory_frost": "Frost",
        "inventory_full": "Inventaret er fullt",
        "inventory_immune": "Immun",
        "inventory_lightning": "Lyn",
        "inventory_logs": "Meldingslogg",
        "inventory_logs_new": "Nye opplåsinger i meldingslogg.",
        "inventory_maxquality": "Høgste kvalitet",
        "inventory_move": "Flytt",
        "inventory_new": "Ny gjenstand",
        "inventory_onlyoneingredient": "Denne oppskrifta krev berre éin av ingrediensane som er viste.",
        "inventory_pickaxe": "Hakke",
        "inventory_pickup": "Plukk opp",
        "inventory_pierce": "Spidd",
        "inventory_poison": "Gift",
        "inventory_pvp": "Ta skade frå andre spelarar (PVP)",
        "inventory_quality": "Kvalitet",
        "inventory_recipes": "Oppskrifter",
        "inventory_repairbutton": "Vøl ein gjenstand",
        "inventory_resistant": "Motstandsfør",
        "inventory_selectedgp": "Vald Forvist kraft",
        "inventory_siege": "Beleiring",
        "inventory_skills": "Evner",
        "inventory_slash": "Kutt",
        "inventory_slightlyresistant": "Litt motstandsfør",
        "inventory_slightlyweak": "Litt veik",
        "inventory_spirit": "Ånd",
        "inventory_split": "Del",
        "inventory_splitstack": "Del stabel",
        "inventory_stackall": "Plassér stablar",
        "inventory_stationlevel": "Stasjonsnivå (Hev ved å byggje betringar)",
        "inventory_stationlevelreq": "Påkravd stasjonsnivå",
        "inventory_style": "Stil",
        "inventory_tabs": "Endre vindauge",
        "inventory_takeall": "Ta alt",
        "inventory_texts": "Valheim-leksikon??",
        "inventory_totalskill": "Total evne",
        "inventory_transfer": "Flytt",
        "inventory_trophies": "Trofé",
        "inventory_upgrade": "Betre kvalitet på $1 til $2",
        "inventory_upgradebutton": "Betre",
        "inventory_use": "Nytt/ta på",
        "inventory_veryresistant": "Veldig motstandsfør",
        "inventory_veryweak": "Veldig veik",
        "inventory_weak": "Veik",
        "item_amber": "Rav",
        "item_amber_description": "&lt;color=yellow&gt;Verdifull",
        "item_amberpearl": "Ravperle",
        "item_amberpearl_description": "&lt;color=yellow&gt;Verdifull",
        "item_ancientroot": "Eldgamal Rot",
        "item_ancientroot_empty": "Den eldgamle rota ser heilt uttørka ut",
        "item_ancientroot_full": "Den eldgamle rota pulsar med energi",
        "item_ancientroot_half": "Gløden frå den eldgamle rota falmer",
        "item_ancientseed": "Eldgamalt Frø",
        "item_ancientseed_description": "Når du held det mot øyret, høyrer du kviskring frå innsida...",
        "item_armor": "Rustning",
        "item_arrow_bronze": "Pil med Bronsespiss",
        "item_arrow_bronze_description": "Kvassare enn flint. Ein skinande bodbringar frå Dauden.",
        "item_arrow_carapace": "Skalpil",
        "item_arrow_carapace_description": "Tung og kvass, denne gjer vondt.",
        "item_arrow_charred": "Svidd Pil",
        "item_arrow_charred_description": "Denne pila er spikka frå eit svidd lårbein, og er hard som metall.",
        "item_arrow_fire": "Eldpil",
        "item_arrow_fire_description": "Denne pila setjer fyr på kva enn ho treffer.",
        "item_arrow_flint": "Pil med Flintspiss",
        "item_arrow_flint_description": "Ein skinnbrytar med hovud av flint.",
        "item_arrow_frost": "Frostpil",
        "item_arrow_frost_description": "Ein spiddande isjøkul.",
        "item_arrow_iron": "Pil med Jarnspiss",
        "item_arrow_iron_description": "Med jarnhette og mørke fjør.",
        "item_arrow_needle": "Nålpil",
        "item_arrow_needle_description": "Det siste stinget.",
        "item_arrow_obsidian": "Obsidianpil",
        "item_arrow_obsidian_description": "Ei flis av mørker.",
        "item_arrow_poison": "Giftpil",
        "item_arrow_poison_description": "Eit bittert stikk frå langt unna.",
        "item_arrow_silver": "Sylvpil",
        "item_arrow_silver_description": "Ei nål som roar rastlause ånder.",
        "item_arrow_wood": "Trepil",
        "item_arrow_wood_description": "Ei pil spikka ut av tre.",
        "item_askbladder": "Osksvinblære",
        "item_askbladder_description": "Ei sur lukt heng framleis att.",
        "item_askhide": "Osksvinskinn",
        "item_askhide_description": "Dette hardføre lêret er tjukt og framleis varmt.",
        "item_asksvin_egg": "Osksvinegg",
        "item_asksvin_egg_description": "Hardt som fjell, men du kan anse noko på innsida. Du bør halde det varmt.",
        "item_asksvin_meat": "Osksvinhale",
        "item_asksvin_meat_cooked": "Steikt Osksvinhale",
        "item_asksvin_meat_cooked_description": "Dette kjøtet har ein kraftig og mogen smak, men er veldig godt viss du steikjer det rett.",
        "item_asksvin_meat_description": "Luktar røyk, sjølv om det er rått.",
        "item_asksvincarrionneck": "Osksvinnakke",
        "item_asksvincarrionneck_description": "Ein hals som syng på siste verset.",
        "item_asksvincarrionpelvic": "Osksvinbekken",
        "item_asksvincarrionpelvic_description": "Bekkenet til ein firføtt skapning.",
        "item_asksvincarrionribcage": "Osksvinsidebein",
        "item_asksvincarrionribcage_description": "Desse sidebeina er gnegne heilt reine.",
        "item_asksvincarrionskull": "Osksvinskalle",
        "item_asksvincarrionskull_description": "Ein tjukk skalle med plass til ein overraskande stor hjerne.",
        "item_atgeir_blackmetal": "Svartmetallatgeir",
        "item_atgeir_blackmetal_description": "Ei frykteleg øks av nesten uknuseleg svartmetall.",
        "item_atgeir_bronze": "Bronseatgeir",
        "item_atgeir_bronze_description": "Reiskapen til ein sann krigar.",
        "item_atgeir_himminafl": "Himminafl",
        "item_atgeir_himminafl_description": "Det er kanskje ikkje ein hamar, men Tor sjølv hadde likte dette våpenet.",
        "item_atgeir_iron": "Jarnatgeir",
        "item_atgeir_iron_description": "Bloddrikkar, skalleknusar, daudebringar.",
        "item_atgeir_wood": "Treatgeir",
        "item_atgeir_wood_description": "Han gjer kanskje ikkje så vondt, men han når langt!",
        "item_axe_berzerkr": "Berserkøkser",
        "item_axe_berzerkr_blood": "Blødande Berserkøkser",
        "item_axe_berzerkr_blood_description": "Jo nærmare dauda du er, dess hardare slår du.",
        "item_axe_berzerkr_description": "Lat raseriet take over og snu deg mot slaktinga.",
        "item_axe_berzerkr_lightning": "Torande Berserkøkser",
        "item_axe_berzerkr_lightning_description": "Blodbadet spreier seg når du svingar desse øksene, slik at Tor sjølv hadde vore stolt.",
        "item_axe_berzerkr_nature": "Ville Berserkøkser",
        "item_axe_berzerkr_nature_description": "Villdyret i deg tek over, og naturen rundt deg strekkjer ut ei hand.",
        "item_axe_blackmetal": "Svartmetalløks",
        "item_axe_blackmetal_description": "Ei perfekt balansert øks smidd frå eit mørkt metall med smaragdglimt.",
        "item_axe_bronze": "Bronseøks",
        "item_axe_bronze_description": "Eit blankpolert blad, bøygd som eit glis.",
        "item_axe_flint": "Flintøks",
        "item_axe_flint_description": "Skarpare enn stein.",
        "item_axe_iron": "Jarnøks",
        "item_axe_iron_description": "Skarp og sterk, ven av vedhoggaren.",
        "item_axe_jotunbane": "Jotunbane",
        "item_axe_jotunbane_description": "Ikkje ein gong dei gamle kjempane kunne lide eit giftig bit frå dette våpenet.",
        "item_axe_stone": "Steinøks",
        "item_axe_stone_description": "Ei enkel øks til å hogge ned tre.",
        "item_axe_wood": "Treøks",
        "item_axe_wood_description": "Hadde det ikkje vore rart om denne øksa kunne hogge ved?",
        "item_backstab": "Bakhaldsåtak",
        "item_barberkit": "Frisørsett",
        "item_barberkit_description": "Eit eigna sett for dei fjongaste frisørar.",
        "item_barley": "Bygg",
        "item_barley_description": "Ein bunt med bygg.",
        "item_barleyflour": "Byggmel",
        "item_barleyflour_description": "Bra å bake brød med.",
        "item_barleywine": "Byggvin for Eldmotstand",
        "item_barleywine_description": "Rustar deg mot eld.",
        "item_barleywinebase": "Byggvinvørter: Eldmotstand",
        "item_barrelrings": "Tynneband",
        "item_barrelrings_description": "Desse metallringane er heilt runde, slik at dei lett kan halde saman ei tynne. Du treng berre å leggje til treverk!",
        "item_battleaxe": "Stridsøks",
        "item_battleaxe_blackmetal": "Svartmetallstridsøks",
        "item_battleaxe_blackmetal_description": "Grønt vert det siste fiendane dine ser før du kløyver dei i to.",
        "item_battleaxe_crystal": "Krystallstridsøks",
        "item_battleaxe_crystal_description": "Du kan sjå gjennom ho, og ho kan slå gjennom deg.",
        "item_battleaxe_description": "Skallekløyvar, ein krigardraum.",
        "item_battleaxe_skullsplittur": "Skallekløyvur",
        "item_battleaxe_skullsplittur_description": "Finner skallar å kløyve, sjølv i den tjukkaste skodda.",
        "item_battleaxe_wood": "Stridsøks av tre",
        "item_battleaxe_wood_description": "Skremmande, men ikkje så skremmande som ei ekte ei.",
        "item_beechseeds": "Bøkefrø",
        "item_beechseeds_description": "Plant dei, så får du eit bøketre.",
        "item_bell": "Bjølle",
        "item_bell_description": "Kven ringjer bjølla for?",
        "item_bellfragment": "Bjøllebrot",
        "item_bellfragment_description": "Dette eldgamle brotet verkar å kome frå ei knust bjølle...",
        "item_beltstrength": "Megingjord",
        "item_beltstrength_description": "Gjer beraren overmenneskeleg styrke.",
        "item_bilebag": "Gallblåse",
        "item_bilebag_description": "Tærande gall frå liket av ein gjall.",
        "item_bilebomb": "Gallbombe",
        "item_bilebomb_description": "Ver varsam.",
        "item_birchseeds": "Bjørkefrø",
        "item_birchseeds_description": "Plant dei, så får du ei bjørk.",
        "item_bjorn_meat": "Bjørnekjøt",
        "item_bjorn_meat_cooked": "Steikt Bjørnekjøtt",
        "item_bjorn_meat_cooked_description": "Smakar som siger.",
        "item_bjorn_meat_description": "Dette feite kjøtet skulle ein gong halde ein bjørn i live gjennom vinterdvalen.",
        "item_bjornhide": "Bjørnefell",
        "item_bjornhide_description": "Ein tjukk og loden fell. Gròv, men framleis mjuk.",
        "item_bjornpaw": "Bjørnelabb",
        "item_bjornpaw_description": "Skarpe klør, eigna til å plukke bær – eller til å lemleste.",
        "item_blackcore": "Svart Kjerne",
        "item_blackcore_description": "Fylt til randa med eldgamal kraft.",
        "item_blackmarble": "Svart Marmor",
        "item_blackmarble_description": "Ei solid steinblokk med skiftande leter i saumane.",
        "item_blackmetal": "Svartmetall",
        "item_blackmetal_description": "Ein tung barre av mørkt metall.",
        "item_blackmetalscrap": "Svartmetallskrap",
        "item_blackmetalscrap_description": "Ein vriden klump med mørkt metall.",
        "item_blacksoup": "Svartsuppe",
        "item_blacksoup_description": "Ei fullkomen jamvekt av søte og syre.",
        "item_blackwood": "Osketre",
        "item_blackwood_description": "Treverk herda av eld og oske.",
        "item_blobvial": "Flaske med Kork",
        "item_blobvial_description": "Tjukk nok til å halde på noko flyktig, men skøyr nok til å verte knust.",
        "item_blockarmor": "Sperrerustning",
        "item_blockforce": "Sperrekraft",
        "item_blockpower": "Sperreevne",
        "item_bloodbag": "Blodsekk",
        "item_bloodbag_description": "Innmaten til ei igle. Æsj!",
        "item_bloodclot": "Blodpropp",
        "item_bloodclot_description": "Ver varsam så han ikkje sprekk medan du ber han...",
        "item_bloodpudding": "Blodpudding",
        "item_bloodpudding_description": "Han er fælsleg god.",
        "item_blueberries": "Blåbær",
        "item_blueberries_description": "Bitte små, men gode på smak.",
        "item_boar_meat": "Villsvinkjøt",
        "item_boar_meat_cooked": "Steikt Villsvinkjøt",
        "item_boar_meat_cooked_description": "Ein verdsleg smak.",
        "item_boarjerky": "Turka Villsvinkjøt",
        "item_boarjerky_description": "Magert og salt.",
        "item_bolt_blackmetal": "Svartmetallbolt",
        "item_bolt_blackmetal_description": "Ein blank bolt av mørkt metall.",
        "item_bolt_bone": "Beinbolt",
        "item_bolt_bone_description": "Ein bolt, grovt skoren ut av gulna bein.",
        "item_bolt_carapace": "Skalbolt",
        "item_bolt_carapace_description": "Ein tung og solid bolt.",
        "item_bolt_charred": "Svidd Bolt",
        "item_bolt_charred_description": "Eit kraftig bein frå ein underarm, forma til ein daudbringande bolt.",
        "item_bolt_iron": "Jarnbolt",
        "item_bolt_iron_description": "Ein kraftig jarnmissil.",
        "item_bombblob_frost": "Klattbombe: Frost",
        "item_bombblob_frost_description": "Om du held ho for lenge, kan handa di fryse fast.",
        "item_bombblob_lava": "Klattbombe: Lava",
        "item_bombblob_lava_description": "Flaska kjennest varm ut, og varslar brann og øydelegging.",
        "item_bombblob_poison": "Klattbombe: Gift",
        "item_bombblob_poison_description": "Det er tilrådeleg å vere varsam om denne flaska knusar.",
        "item_bombblob_poisonelite": "Klattbombe: Elitegift",
        "item_bombblob_poisonelite_description": "Ikkje tilrådeleg å ande inn.",
        "item_bombblob_tar": "Klattbombe: Tjøre",
        "item_bombblob_tar_description": "Det kleimne emnet på innsida pulsar, liksom på trugande vis.",
        "item_bonefragments": "Beinsplintar",
        "item_bonefragments_description": "Ein haug med knuste bein.",
        "item_bonemawmeat": "Beingapkjøt",
        "item_bonemawmeat_cooked": "Steikt Beingapkjøt",
        "item_bonemawmeat_cooked_description": "Det vart ikkje påverka av kokande sjø, men å steike kjøtet over open eld gjorde det herleg sprøtt.",
        "item_bonemawmeat_description": "God kvit fisk. Styrkjer beingrinda!",
        "item_bonemawscale": "Beingapskjel",
        "item_bonemawscale_description": "Ser nett ut som bein. Best å ikkje tenkje for mykje over samansetjinga til denne skapningen...",
        "item_bonemawtooth": "Beingaptann",
        "item_bonemawtooth_description": "Har drepe mang ein modig sjømann.",
        "item_bow": "Grov Boge",
        "item_bow_ashlands": "Osketann",
        "item_bow_ashlands_description": "Reist att or oska, denne boga held ukueleg styrke.",
        "item_bow_ashlandsblood": "Blodtann",
        "item_bow_ashlandsblood_description": "Piler skotne or denne boga skjer gjennom kjøt med unmatched ferocity.",
        "item_bow_ashlandsroot": "Rottann",
        "item_bow_ashlandsroot_description": "Som ei vridande grein was made to seek the sun, this bow was made to seek the slaughter.",
        "item_bow_ashlandsstorm": "Stormtann",
        "item_bow_ashlandsstorm_description": "Lat pilene dine fly snøgt som lynet.",
        "item_bow_description": "Ei enkel, men nyttande boge.",
        "item_bow_draugrfang": "Draugtann",
        "item_bow_draugrfang_description": "Utskoren i mørkt tre og spent opp med ei glitrande sene. Ein frykteleg ting.",
        "item_bow_finewood": "Finvedboge",
        "item_bow_finewood_description": "Ei enkel boge i sterkt og spenstig tre.",
        "item_bow_huntsman": "Jegerboge",
        "item_bow_huntsman_description": "Satt i stand på meisterleg vis. Som or draumen til ein jeger.",
        "item_bow_snipesnap": "Virvelknusar",
        "item_bow_snipesnap_description": "Du kan brått skade ryggen i freistnaden på å spenne denne boga, men det er ho verd.",
        "item_bread": "Brød",
        "item_bread_description": "Eit godt brød.",
        "item_breaddough": "Brøddeig",
        "item_breaddough_description": "Klar for omnen.",
        "item_bronze": "Bronse",
        "item_bronze_description": "Ei sterk legering av kopar og tinn.",
        "item_bronzenails": "Bronsenaglar",
        "item_bronzenails_description": "Vert nytta både til skip og innbu.",
        "item_bronzescrap": "Bronseskrap",
        "item_bronzescrap_description": "Det er gamalt og eira, men kan smeltast og nyttast om att.",
        "item_bug_meat": "Dronekjøt",
        "item_bug_meat_cooked": "Steikt Dronekjøt",
        "item_bug_meat_cooked_description": "Saftig kvitt kjøt. Nesten utan like.",
        "item_bug_meat_description": "Når du kjem deg gjennom skalet, finn du møyrt og saftig kjøt på innsida.",
        "item_candlewick": "Veik",
        "item_candlewick_description": "Når du støypar desse inn i voks, får du eit koseleg ljos som brenn lenge.",
        "item_cape_ash": "Oskekappe",
        "item_cape_ash_description": "Kappa har eit vakkert mønster vove inn med fin metalltråd, lik ei skjebne voven av Nornene sjølve.",
        "item_cape_asksvin": "Osksvinkappe",
        "item_cape_asksvin_description": "Denne tjukke kappa fangar vinden, mest som seglet på eit skip.",
        "item_cape_deerhide": "Rådyrkappe",
        "item_cape_deerhide_description": "Hòlebuar-chic.",
        "item_cape_feather": "Fjørkappe",
        "item_cape_feather_description": "Kappa gjer at du kjenner deg lettare, mest som om du kan flyge!",
        "item_cape_linen": "Linkappe",
        "item_cape_linen_description": "Ei enkel kappe for reisande.",
        "item_cape_lox": "Stutfislekappe",
        "item_cape_lox_description": "Fellen frå eit av dei veldige beista. Han er tjukk og varm.",
        "item_cape_odin": "Odinskappe",
        "item_cape_odin_description": "Dei fremste krigarane til Odin skal ha det finaste tøyet.",
        "item_cape_trollhide": "Trollskinnskappe",
        "item_cape_trollhide_description": "Trollskinn er smidig og slitesterkt.",
        "item_cape_wolf": "Vargeskinnskappe",
        "item_cape_wolf_description": "Vargen er fødd til å overleve. Denne hadde bare uflaks. No held fellen hans deg varm i snøen.",
        "item_carapace": "Skal",
        "item_carapace_description": "Ei plate av kitinrustning.",
        "item_carrot": "Gulrot",
        "item_carrot_description": "Ei raudgul godsak.",
        "item_carrotseeds": "Gulrotfrø",
        "item_carrotseeds_description": "Plant desse om du tykkjer om gulrøter...",
        "item_carrotsoup": "Gulrotsuppe",
        "item_carrotsoup_description": "Ei varm og velsmakande suppe laga på gulrøter.",
        "item_catapult_ammo": "Sprengladning",
        "item_catapult_ammo_description": "Ladning for katapultar. Ver varsam.",
        "item_catapult_training_ammo": "Graustensladning",
        "item_catapult_training_ammo_description": "Ladning for katapultar. Sjå opp for knuselege ting.",
        "item_celestialfeather": "Himmelfjør",
        "item_celestialfeather_description": "Einaste leivd etter ei fallen valkyrje.",
        "item_ceramicplate": "Kjeramikkplate",
        "item_ceramicplate_description": "Kor varm utsida av plata enn vert, held innsida seg merkeleg kjølen.",
        "item_chain": "Jarnlekkje",
        "item_chain_description": "Ei lekkje av jarnringar.",
        "item_chancetoapplyse": "Sannsyn for verknad:",
        "item_charcoalresin": "Charcoal Resin",
        "item_charcoalresin_description": "The resin from a tree that was set ablaze a long time ago. It's still ready to burn some more.",
        "item_charredbone": "Charred Bone",
        "item_charredbone_description": "Followed by the distinct smell of burnt meat.",
        "item_charredcogwheel": "Charred Cogwheel",
        "item_charredcogwheel_description": "This could be used for some clever machinery...",
        "item_charredskull": "Charred Skull",
        "item_charredskull_description": "The blackened skull of a long-dead warrior. It's unlikely that a proper burial would grant them any peace.",
        "item_chest_berserker": "Patterns of the Bear",
        "item_chest_berserker_description": "If these intricate designs can protect warriors from distant lands, they can surely protect you too.",
        "item_chest_berserker_undead": "Vilebone Cage",
        "item_chest_berserker_undead_description": "Crafted from the shattered bones of a tormented bear.",
        "item_chest_bronze": "Bronze Plate Tunic",
        "item_chest_bronze_description": "A breastplate of hammered bronze.",
        "item_chest_carapace": "Carapace Breastplate",
        "item_chest_carapace_description": "A breastplate crafted from the burnished carapace of a giant insect.",
        "item_chest_dress1": "Plain Brown Dress",
        "item_chest_dress1_description": "A plain brown dress, worn over a blue underdress.",
        "item_chest_dress10": "Simple Undyed Dress",
        "item_chest_dress10_description": "A simple dress for everyday wear.",
        "item_chest_dress2": "Brown Dress with Shawl",
        "item_chest_dress2_description": "A brown dress, with a matching shawl around the shoulders. Warm and stylish!",
        "item_chest_dress3": "Brown Dress with Beads",
        "item_chest_dress3_description": "A fancy brown dress, with beads and silver fibula brooches. Excellent for a feast!",
        "item_chest_dress4": "Plain Blue Dress",
        "item_chest_dress4_description": "A plain blue dress, worn over a red underdress.",
        "item_chest_dress5": "Blue Dress with Shawl",
        "item_chest_dress5_description": "A blue dress, with a green shawl around the shoulders. Warm and stylish!",
        "item_chest_dress6": "Blue Dress with Beads",
        "item_chest_dress6_description": "A fancy blue dress, with beads and bronze fibula brooches. Excellent for a feast!",
        "item_chest_dress7": "Plain Yellow Dress",
        "item_chest_dress7_description": "A plain yellow dress, worn over a green underdress.",
        "item_chest_dress8": "Yellow Dress with Shawl",
        "item_chest_dress8_description": "A yellow dress, with a purple shawl around the shoulders. Warm and stylish!",
        "item_chest_dress9": "Yellow Dress with Beads",
        "item_chest_dress9_description": "A fancy yellow dress, with beads and silver fibula brooches. Excellent for a feast!",
        "item_chest_fenris": "Fenris Coat",
        "item_chest_fenris_description": "The beast could draw deep breaths, so that its howl could be heard far across the land.",
        "item_chest_flametal": "Flametal Breastplate",
        "item_chest_flametal_description": "This fusion of mysterious flametal and charred bones serves as a protective layer more resilient than anything you could ever find in Midgard.",
        "item_chest_harvester1": "Harvest Tunic",
        "item_chest_harvester1_description": "When working the fields, it's important to dress accordingly. A shorter tunic lets in a cool breeze.",
        "item_chest_harvester2": "Harvest Dress",
        "item_chest_harvester2_description": "When working the fields, it's important to dress accordingly. This long dress keeps your knees covered while you work.",
        "item_chest_hildir_description": "Property of Hildir, please return if found.",
        "item_chest_hildir1": "Hildir's Brass Chest",
        "item_chest_hildir2": "Hildir's Silver Chest",
        "item_chest_hildir3": "Hildir's Bronze Chest",
        "item_chest_iron": "Iron Scale Mail",
        "item_chest_iron_description": "An iron scale mail, this will turn all but the strongest of blows."
    }
}